[
    {
        "clue": "The simplest, fundamental data types in JavaScript",
        "answer": "primitive"
    },
    {
        "clue": "Represents logical entities and can be either true or false",
        "answer": "boolean"
    },
    {
        "clue": "Represents sequence of characters",
        "answer": "string"
    },
    {
        "clue": "Represents a variable that has not been assigned a value",
        "answer": "undefined"
    },
    {
        "clue": "Represents the intentional absence of any object value",
        "answer": "null"
    }
]